mailbits/__init__.py
mailbits/email2dict.py
mailbits/misc.py
mailbits/py.typed
mailbits-0.2.2.dist-info/METADATA
mailbits-0.2.2.dist-info/WHEEL
mailbits-0.2.2.dist-info/licenses/LICENSE
mailbits-0.2.2.dist-info/RECORD
