Metadata-Version: 2.3
Name: mailbits
Version: 0.2.2
Summary: Assorted e-mail utility functions
Project-URL: Source Code, https://github.com/jwodder/mailbits
Project-URL: Bug Tracker, https://github.com/jwodder/mailbits/issues
Author-email: John Thorvald Wodder II <mailbits@varonathe.org>
License: MIT
Keywords: EmailMessage,content type,e-mail,e-mail address,e-mail comparison,e-mail inspection,email,recipients
Classifier: Intended Audience :: Developers
Classifier: License :: OSI Approved :: MIT License
Classifier: Programming Language :: Python :: 3
Classifier: Programming Language :: Python :: 3 :: Only
Classifier: Programming Language :: Python :: 3.8
Classifier: Programming Language :: Python :: 3.9
Classifier: Programming Language :: Python :: 3.10
Classifier: Programming Language :: Python :: 3.11
Classifier: Programming Language :: Python :: 3.12
Classifier: Programming Language :: Python :: 3.13
Classifier: Programming Language :: Python :: Implementation :: CPython
Classifier: Programming Language :: Python :: Implementation :: PyPy
Classifier: Topic :: Communications :: Email
Classifier: Topic :: Utilities
Classifier: Typing :: Typed
Requires-Python: >=3.8
Requires-Dist: attrs>=18.1
Requires-Dist: typing-extensions; python_version < '3.8'
